pseanalytics/__init__.py
pseanalytics/pseanalytics.py
pseanalytics/strategies.py
pseanalytics-0.0.3.dist-info/DESCRIPTION.rst
pseanalytics-0.0.3.dist-info/METADATA
pseanalytics-0.0.3.dist-info/RECORD
pseanalytics-0.0.3.dist-info/WHEEL
pseanalytics-0.0.3.dist-info/metadata.json
pseanalytics-0.0.3.dist-info/top_level.txt
