Metadata-Version: 2.0
Name: pseanalytics
Version: 0.0.3
Summary: stock trading api
Home-page: https://github.com/kentballon/pseanalytics
Author: Kent Ballon
Author-email: kentballon@gmail.com
License: UNKNOWN
Platform: UNKNOWN
Classifier: Programming Language :: Python :: 3
Classifier: License :: OSI Approved :: MIT License
Classifier: Operating System :: OS Independent
Requires-Python: >= 2.7
